snowflake_utils/__init__.py
snowflake_utils/snowflake_id.py
snowflake_utils/snowflake_id_generator.py
snowflake_utils/types.py
snowflake_utils-0.1.3.dist-info/LICENSE
snowflake_utils-0.1.3.dist-info/METADATA
snowflake_utils-0.1.3.dist-info/WHEEL
snowflake_utils-0.1.3.dist-info/RECORD
