Metadata-Version: 2.1
Name: snowflake-utils
Version: 0.1.3
Summary: Utilities for generating and verifying snowflake ids
Home-page: https://impalah.github.io/snowflake-utils/
License: MIT
Keywords: snowflake,id,utilities
Author: impalah
Author-email: impalah@gmail.com
Requires-Python: >=3.10
Classifier: Development Status :: 4 - Beta
Classifier: Intended Audience :: Developers
Classifier: License :: OSI Approved :: MIT License
Classifier: Programming Language :: Python :: 3
Classifier: Programming Language :: Python :: 3.10
Classifier: Programming Language :: Python :: 3.11
Classifier: Programming Language :: Python :: 3.12
Classifier: Topic :: Software Development :: Libraries :: Python Modules
Project-URL: Documentation, https://impalah.github.io/snowflake-utils/
Project-URL: Repository, https://github.com/impalah/snowflake-utils
Project-URL: Source, https://github.com/impalah/snowflake-utils
